libpip2pi/__init__.py
libpip2pi/commands.py
pip2pi-0.8.2.dist-info/LICENSE.txt
pip2pi-0.8.2.dist-info/METADATA
pip2pi-0.8.2.dist-info/WHEEL
pip2pi-0.8.2.dist-info/entry_points.txt
pip2pi-0.8.2.dist-info/top_level.txt
pip2pi-0.8.2.dist-info/RECORD
