Metadata-Version: 2.1
Name: pip2pi
Version: 0.8.2
Summary: pip2pi builds a PyPI-compatible package repository from pip requirements
Home-page: https://github.com/wolever/pip2pi
Author: David Wolever
Author-email: david@wolever.net
Maintainer: Md Safiyat Reza
Maintainer-email: safiyat@voereir.com
License: BSD
Platform: UNKNOWN
Classifier: Development Status :: 4 - Beta
Classifier: Environment :: Console
Classifier: Intended Audience :: Developers
Classifier: Intended Audience :: System Administrators
Classifier: License :: OSI Approved :: BSD License
Classifier: Natural Language :: English
Classifier: Operating System :: OS Independent
Classifier: Programming Language :: Python
Classifier: Topic :: Software Development
Classifier: Topic :: Utilities
License-File: LICENSE.txt
Requires-Dist: pip (>=1.1)
